productservice/Utils.py
productservice/__init__.py
ProductService-0.0.1.dist-info/METADATA
ProductService-0.0.1.dist-info/WHEEL
ProductService-0.0.1.dist-info/top_level.txt
ProductService-0.0.1.dist-info/RECORD
