Metadata-Version: 2.1
Name: ProductService
Version: 0.0.1
Summary: Product Service Python SDK
Home-page: UNKNOWN
Author: Siddhant Khanna
License: UNKNOWN
Platform: UNKNOWN
